namecheck/cli.py
namecheck/utils.py
namecheck/render/const.py
namecheck/render/utils.py
namecheck-2025.11.13.dist-info/METADATA
namecheck-2025.11.13.dist-info/WHEEL
namecheck-2025.11.13.dist-info/entry_points.txt
namecheck-2025.11.13.dist-info/licenses/LICENSE
namecheck-2025.11.13.dist-info/RECORD
