Metadata-Version: 2.4
Name: namecheck
Version: 2025.11.13
Summary: CLI tool to check the availability of a package name on PyPI and TestPyPI
Project-URL: Homepage, https://github.com/pixelprotest/namecheck
Project-URL: Bug Tracker, https://github.com/pixelprotest/namecheck/issues
Author-email: pixelprotest <hello@pixelprotest.com>
License: MIT
License-File: LICENSE
Classifier: Development Status :: 4 - Beta
Classifier: Intended Audience :: Developers
Classifier: License :: OSI Approved :: MIT License
Classifier: Programming Language :: Python :: 3.10
Classifier: Programming Language :: Python :: 3.11
Classifier: Programming Language :: Python :: 3.12
Classifier: Topic :: Utilities
Requires-Python: >=3.10
Requires-Dist: beautifulsoup4>=4.14.2
Requires-Dist: platformdirs>=4.0.0
Requires-Dist: requests>=2.31.0
Requires-Dist: rich>=13.8.1
Provides-Extra: dev
Requires-Dist: pytest-cov>=4.1.0; extra == 'dev'
Requires-Dist: pytest>=7.4.4; extra == 'dev'
